neuroshard/__init__.py
neuroshard/cli.py
neuroshard/commands/checkout.py
neuroshard/commands/commit.py
neuroshard/commands/diff.py
neuroshard/commands/gc.py
neuroshard/commands/git_init.py
neuroshard/commands/init.py
neuroshard/commands/pull.py
neuroshard/commands/push.py
neuroshard/commands/status.py
neuroshard/commands/track.py
neuroshard/core/__init__.py
neuroshard/core/chunker.py
neuroshard/core/gc.py
neuroshard/core/index.py
neuroshard/core/manifest.py
neuroshard/core/remote.py
neuroshard/core/store.py
neuroshard/server/__init__.py
neuroshard/server/app.py
neuroshard-0.1.1.dist-info/METADATA
neuroshard-0.1.1.dist-info/WHEEL
neuroshard-0.1.1.dist-info/entry_points.txt
neuroshard-0.1.1.dist-info/top_level.txt
neuroshard-0.1.1.dist-info/RECORD
