Metadata-Version: 2.4
Name: neuroshard
Version: 0.1.1
Summary: Git for AI models. Fast. Deduplicated. Reproducible.
Author-email: Shard Team <hello@shard.dev>
Classifier: Programming Language :: Python :: 3
Classifier: License :: OSI Approved :: MIT License
Classifier: Operating System :: OS Independent
Requires-Python: >=3.8
Requires-Dist: typer>=0.9.0
Requires-Dist: zstandard>=0.21.0
Requires-Dist: requests>=2.31.0
Requires-Dist: fastapi>=0.100.0
Requires-Dist: uvicorn>=0.23.0
